{
	"hot": [{
		"userid": "29154820",
		"userhead": "http://pic.qiushibaike.com/system/avtnew/2915/29154820/thumb/2016120621455274.JPEG?imageView2/1/w/90/h/90",
		"username": "岁月是把杀豬刀 2628\n吹牛逼，吹牛逼，又见明哥吹牛逼。。。。",
		"usersex": "manIcon",
		"userage": "26",
		"comment": "吹牛逼，吹牛逼，又见明哥吹牛逼。。。。",
		"sum": "28"
	}, {
		"userid": "28437800",
		"userhead": "http://pic.qiushibaike.com/system/avtnew/2843/28437800/thumb/2016112723370321.JPEG?imageView2/1/w/90/h/90",
		"username": "【星空】白月光 6116\n看热闹了看热闹了，明哥要倒霉了\u0001[笑哭]\u0001[笑哭]",
		"usersex": "womenIcon",
		"userage": "61",
		"comment": "看热闹了看热闹了，明哥要倒霉了\u0001[笑哭]\u0001[笑哭]",
		"sum": "16"
	}, {
		"userid": "30501602",
		"userhead": "http://pic.qiushibaike.com/system/avtnew/3050/30501602/thumb/2016112507515575.JPEG?imageView2/1/w/90/h/90",
		"username": "巫女～<素素> 2614\n扎猛子\u0001[大笑]\u0001[大笑]\u0001[大笑]",
		"usersex": "womenIcon",
		"userage": "26",
		"comment": "扎猛子\u0001[大笑]\u0001[大笑]\u0001[大笑]",
		"sum": "14"
	}, {
		"userid": "29248956",
		"userhead": "http://pic.qiushibaike.com/system/avtnew/2924/29248956/thumb/2016120115244373.JPEG?imageView2/1/w/90/h/90",
		"username": "【星空】小燕飞 3013\n这个撞的是母牛吧？我擦",
		"usersex": "manIcon",
		"userage": "30",
		"comment": "这个撞的是母牛吧？我擦",
		"sum": "13"
	}, {
		"userid": "32814675",
		"userhead": "http://pic.qiushibaike.com/system/avtnew/3281/32814675/thumb/2016112223402821.JPEG?imageView2/1/w/90/h/90",
		"username": "鲨鱼姑娘 9911\n牛逼大了\u0001[doge]\u0001[doge]",
		"usersex": "womenIcon",
		"userage": "99",
		"comment": "牛逼大了\u0001[doge]\u0001[doge]",
		"sum": "11"
	}, {
		"userid": "12992639",
		"userhead": "http://pic.qiushibaike.com/system/avtnew/1299/12992639/thumb/20160414185851.jpg?imageView2/1/w/90/h/90",
		"username": "胖香 2910\n卧槽！撒泼完毕，走人！",
		"usersex": "womenIcon",
		"userage": "29",
		"comment": "卧槽！撒泼完毕，走人！",
		"sum": "10"
	}, {
		"userid": "12992639",
		"userhead": "http://pic.qiushibaike.com/system/avtnew/1299/12992639/thumb/20160414185851.jpg?imageView2/1/w/90/h/90",
		"username": "胖香 2910\n卧槽！抖哥有没有也这么做，去怼了牛屁股，，\u0001[幻想]",
		"usersex": "womenIcon",
		"userage": "29",
		"comment": "卧槽！抖哥有没有也这么做，去怼了牛屁股，，\u0001[幻想]",
		"sum": "10"
	}, {
		"userid": "10606806",
		"userhead": "http://pic.qiushibaike.com/system/avtnew/1060/10606806/thumb/2016120219293146.JPEG?imageView2/1/w/90/h/90",
		"username": "【星空】忧伤 279\n卧槽，真的有人能用头顶牛…还是顶的牛屁股",
		"usersex": "manIcon",
		"userage": "27",
		"comment": "卧槽，真的有人能用头顶牛…还是顶的牛屁股",
		"sum": "9"
	}, {
		"userid": "30201529",
		"userhead": "http://pic.qiushibaike.com/system/avtnew/3020/30201529/thumb/2016092816272530.JPEG?imageView2/1/w/90/h/90",
		"username": "【星空】堂主 379\n然后一头牛屎",
		"usersex": "manIcon",
		"userage": "37",
		"comment": "然后一头牛屎",
		"sum": "9"
	}, {
		"userid": "28711746",
		"userhead": "http://pic.qiushibaike.com/system/avtnew/2871/28711746/thumb/201609210221000.JPEG?imageView2/1/w/90/h/90",
		"username": "【星空】小静 998\n这么厉害",
		"usersex": "womenIcon",
		"userage": "99",
		"comment": "这么厉害",
		"sum": "8"
	}],
	"gen": [{
		"userid": "19072017",
		"userhead": "http://pic.qiushibaike.com/system/avtnew/1907/19072017/thumb/20160625074036.jpg",
		"username": "楚留臭臭",
		"comment": "头差进去了吗",
		"sum": "81"
	}, {
		"userid": "32058095",
		"userhead": "http://pic.qiushibaike.com/system/avtnew/3205/32058095/thumb/20160627233354.jpg",
		"username": "输入新的用户名子",
		"comment": "是撞进了吧",
		"sum": "80"
	}, {
		"userid": "10014635",
		"userhead": "http://pic.qiushibaike.com/system/avtnew/1001/10014635/thumb/20150804123340.jpg",
		"username": "海豚牙",
		"comment": "所以明哥的头是扁的？",
		"sum": "79"
	}, {
		"userid": "6616403",
		"userhead": "http://pic.qiushibaike.com/system/avtnew/661/6616403/thumb/2016091821344358.JPEG",
		"username": "流年＆染指寂寞",
		"comment": "我就是关心他进去了没",
		"sum": "78"
	}, {
		"userid": "31259535",
		"userhead": "http://pic.qiushibaike.com/system/avtnew/3125/31259535/thumb/20160428234603.jpg",
		"username": "没事看看解闷",
		"comment": "顶的母牛一声哀嚎",
		"sum": "77"
	}, {
		"userid": "27158774",
		"userhead": "http://pic.qiushibaike.com/system/avtnew/2715/27158774/thumb/20150407194330.jpg",
		"username": "迈克尔.杰克孙",
		"comment": "脑袋进去了？",
		"sum": "76"
	}, {
		"userid": "31845696",
		"userhead": "http://pic.qiushibaike.com/system/avtnew/3184/31845696/thumb/20160526143356.jpg",
		"username": "我的名字不伤感",
		"comment": "河南人",
		"sum": "75"
	}, {
		"userid": "30934705",
		"userhead": "http://pic.qiushibaike.com/system/avtnew/3093/30934705/thumb/2016120615023344.JPEG",
		"username": "王-不留寝",
		"comment": "塞进去了？",
		"sum": "74"
	}, {
		"userid": "11625234",
		"userhead": "http://pic.qiushibaike.com/system/avtnew/1162/11625234/thumb/2016101015402936.JPEG",
		"username": "公与之乘",
		"comment": "这该是多偏的山村才有这样的河水",
		"sum": "73"
	}, {
		"userid": "7988159",
		"userhead": "http://pic.qiushibaike.com/system/avtnew/798/7988159/thumb/20150608102737.jpg",
		"username": "榆树上的考拉",
		"comment": "咋滴？把脑袋撞进去了？",
		"sum": "71"
	}, {
		"userid": "822279",
		"userhead": "http://static.qiushibaike.com/images/thumb/missing.png",
		"username": "哎，负了友",
		"comment": "然后你们发现了新大陆，从此走上了一条不归路，集体成为老司机，天天堵着微微醉酒和胖香",
		"sum": "70"
	}, {
		"userid": "10252655",
		"userhead": "http://pic.qiushibaike.com/system/avtnew/1025/10252655/thumb/20160416124032.jpg",
		"username": "H飞Z扬G",
		"comment": "头没插进牛逼里？",
		"sum": "69"
	}, {
		"userid": "31105198",
		"userhead": "http://pic.qiushibaike.com/system/avtnew/3110/31105198/thumb/20160203125253.jpg",
		"username": "白开水的人生",
		"comment": "大家忙了一下午，趁牛气喘吁吁的趴在地上时，终于把明哥的头拔出来",
		"sum": "68"
	}, {
		"userid": "21867141",
		"userhead": "http://pic.qiushibaike.com/system/avtnew/2186/21867141/thumb/20160305112721.jpg",
		"username": "赵微跟尔康骑马马",
		"comment": "牛逼啊！",
		"sum": "67"
	}, {
		"userid": "1779220",
		"userhead": "http://pic.qiushibaike.com/system/avtnew/177/1779220/thumb/2016112500280030.JPEG",
		"username": "一只很烧烧滴喵",
		"comment": "额 要吹真的牛 B",
		"sum": "66"
	}, {
		"userid": "26578154",
		"userhead": "http://pic.qiushibaike.com/system/avtnew/2657/26578154/thumb/2016112714410359.JPEG",
		"username": "名字不长无法注册",
		"comment": "水牛被爆菊了？",
		"sum": "65"
	}, {
		"userid": "24826964",
		"userhead": "http://pic.qiushibaike.com/system/avtnew/2482/24826964/thumb/20150116122118.jpg",
		"username": "美磊电子",
		"comment": "牛逼不是吹的，是撞的",
		"sum": "64"
	}, {
		"userid": "18560853",
		"userhead": "http://pic.qiushibaike.com/system/avtnew/1856/18560853/thumb/2016110114525576.JPEG",
		"username": "阿苏勒*吕归尘",
		"comment": "然后被牛一屁崩坏了",
		"sum": "63"
	}, {
		"userid": "6679884",
		"userhead": "http://pic.qiushibaike.com/system/avtnew/667/6679884/thumb/20160617214945.jpg",
		"username": "动动谁试试",
		"comment": "进去了没？多深？",
		"sum": "62"
	}, {
		"userid": "30765218",
		"userhead": "http://pic.qiushibaike.com/system/avtnew/3076/30765218/thumb/20160213124952.jpg",
		"username": "至上直下",
		"comment": "水牛舒服的喔了一声",
		"sum": "61"
	}, {
		"userid": "33071347",
		"userhead": "http://pic.qiushibaike.com/system/avtnew/3307/33071347/thumb/2016120614412713.JPEG",
		"username": "神经质主任",
		"comment": "：牛逼差点被人吹到，吓死牛牛了",
		"sum": "60"
	}, {
		"userid": "18842243",
		"userhead": "http://static.qiushibaike.com/images/thumb/missing.png",
		"username": "八百八十八个笑话",
		"comment": "小时候水好清啊。",
		"sum": "59"
	}, {
		"userid": "17484739",
		"userhead": "http://pic.qiushibaike.com/system/avtnew/1748/17484739/thumb/20150911224328.jpg",
		"username": "swordzxx",
		"comment": "咦，明哥呢？钻进去了吗？咋不见人了？",
		"sum": "58"
	}, {
		"userid": "11331029",
		"userhead": "http://pic.qiushibaike.com/system/avtnew/1133/11331029/thumb/20150302094513.jpg",
		"username": "免注册直接登录",
		"comment": "水草地游泳， 危险！",
		"sum": "57"
	}, {
		"userid": "15018294",
		"userhead": "http://pic.qiushibaike.com/system/avtnew/1501/15018294/thumb/2016113014015629.JPEG",
		"username": "意大利飞机",
		"comment": "如今坟头草都三尺多高了",
		"sum": "56"
	}, {
		"userid": "32269606",
		"userhead": "http://pic.qiushibaike.com/system/avtnew/3226/32269606/thumb/2016103123315124.JPEG",
		"username": "听着情歌跑着调",
		"comment": "楼主家长很美，想想就知道，",
		"sum": "55"
	}, {
		"userid": "21727415",
		"userhead": "http://pic.qiushibaike.com/system/avtnew/2172/21727415/thumb/20141015133903.jpg",
		"username": "天马～～空",
		"comment": "鼓掌鼓掌，明哥真牛逼，快看明哥牛逼不？",
		"sum": "54"
	}, {
		"userid": "30922709",
		"userhead": "http://pic.qiushibaike.com/system/avtnew/3092/30922709/thumb/201611301157558.JPEG",
		"username": "你好，我是小贱贱",
		"comment": "这是赶着重新投胎么？",
		"sum": "53"
	}, {
		"userid": "30653062",
		"userhead": "http://pic.qiushibaike.com/system/avtnew/3065/30653062/thumb/20151120191136.jpg",
		"username": "—没名字—",
		"comment": "结果母牛说 哇 好舒服 再来几次",
		"sum": "52"
	}, {
		"userid": "13515237",
		"userhead": "http://pic.qiushibaike.com/system/avtnew/1351/13515237/thumb/20160328212529.jpg",
		"username": "猫咪爱吃肉肉",
		"comment": "他是想哪来回哪去",
		"sum": "51"
	}, {
		"userid": "21215241",
		"userhead": "http://pic.qiushibaike.com/system/avtnew/2121/21215241/thumb/20160313213746.jpg",
		"username": "知足就好了",
		"comment": "还没说完了，那牛不是吓一跳么！那牛粑粑就噼里啪啦下来了！",
		"sum": "50"
	}, {
		"userid": "16175109",
		"userhead": "http://pic.qiushibaike.com/system/avtnew/1617/16175109/thumb/nopic.jpg",
		"username": "弓箭专卖",
		"comment": "看，天上一头牛，后边挂了个脑袋",
		"sum": "49"
	}, {
		"userid": "28551554",
		"userhead": "http://pic.qiushibaike.com/system/avtnew/2855/28551554/thumb/20151130041831.jpg",
		"username": "淡水海星",
		"comment": "现在没有这么清的河了",
		"sum": "48"
	}, {
		"userid": "21388149",
		"userhead": "http://pic.qiushibaike.com/system/avtnew/2138/21388149/thumb/20141006102550.jpg",
		"username": "大裤衩里有小鸡",
		"comment": "水牛突然菊花一紧",
		"sum": "46"
	}, {
		"userid": "12310069",
		"userhead": "http://pic.qiushibaike.com/system/avtnew/1231/12310069/thumb/20141209212801.jpg",
		"username": "怒艹100楼^_^一秒真男人",
		"comment": "水牛：啊……噢……啊……要……还要……使劲……啊嗯",
		"sum": "45"
	}, {
		"userid": "32617822",
		"userhead": "http://pic.qiushibaike.com/system/avtnew/3261/32617822/thumb/2016101800162764.JPEG",
		"username": "局外人、！",
		"comment": "咦！怎么楼主头不见了\u0001[惊讶]",
		"sum": "44"
	}, {
		"userid": "32907606",
		"userhead": "http://pic.qiushibaike.com/system/avtnew/3290/32907606/thumb/2016110122364284.JPEG",
		"username": "喵了个咪啦西",
		"comment": "头没擦牛逼里去吧！",
		"sum": "43"
	}, {
		"userid": "32719197",
		"userhead": "http://pic.qiushibaike.com/system/avtnew/3271/32719197/thumb/201611282351242.JPEG",
		"username": "小小样:",
		"comment": "然后头就拔不出来了",
		"sum": "42"
	}, {
		"userid": "28539336",
		"userhead": "http://pic.qiushibaike.com/system/avtnew/2853/28539336/thumb/20150521002531.jpg",
		"username": "后知后觉又过了秋",
		"comment": "卧槽，这个叼这个叼",
		"sum": "41"
	}, {
		"userid": "32246795",
		"userhead": "http://pic.qiushibaike.com/system/avtnew/3224/32246795/thumb/2016090414260188.JPEG",
		"username": "本尊今日渡劫",
		"comment": "公牛母牛？",
		"sum": "40"
	}, {
		"userid": "33030154",
		"userhead": "http://pic.qiushibaike.com/system/avtnew/3303/33030154/thumb/2016112710134321.GIF",
		"username": "人一猥琐就年轻",
		"comment": "然后牛一脚把你踢成半身不遂了，你天天只能躺着发糗百？",
		"sum": "39"
	}, {
		"userid": "253912",
		"userhead": "http://pic.qiushibaike.com/system/avtnew/25/253912/thumb/2016082612052077.JPEG",
		"username": "王宇航",
		"comment": "从此水牛再也没有享受过那天的性福……",
		"sum": "38"
	}, {
		"userid": "6854890",
		"userhead": "http://static.qiushibaike.com/images/thumb/missing.png",
		"username": "早安柚芷",
		"comment": "我以为是骑牛上了",
		"sum": "37"
	}, {
		"userid": "7390996",
		"userhead": "http://pic.qiushibaike.com/system/avtnew/739/7390996/thumb/20150208153326.jpg",
		"username": "半块儿砖头",
		"comment": "这就是传说中的“装（撞）逼”喽",
		"sum": "36"
	}, {
		"userid": "23324063",
		"userhead": "http://pic.qiushibaike.com/system/avtnew/2332/23324063/thumb/201611272207341.JPEG",
		"username": "永保男儿身",
		"comment": "然后牛一个后蹬腿。这就是lz哥哥傻了的原因！！",
		"sum": "35"
	}, {
		"userid": "31135259",
		"userhead": "http://static.qiushibaike.com/images/thumb/missing.png",
		"username": "微信停信",
		"comment": "还好不是母牛，要不然明哥就进去了。",
		"sum": "34"
	}, {
		"userid": "32928978",
		"userhead": "http://pic.qiushibaike.com/system/avtnew/3292/32928978/thumb/2016110613181870.JPEG",
		"username": "饵--------",
		"comment": "没有一头扎进去吗",
		"sum": "33"
	}, {
		"userid": "18987151",
		"userhead": "http://static.qiushibaike.com/images/thumb/missing.png",
		"username": "于其开开1",
		"comment": "我居然看成撞进牛逼里，糗大了",
		"sum": "32"
	}, {
		"userid": "27054624",
		"userhead": "http://pic.qiushibaike.com/system/avtnew/2705/27054624/thumb/2016120620573930.JPEG",
		"username": "じ飘翎雁",
		"comment": "回复 24楼：小时候哪里都有清澈的河水啊",
		"sum": "31"
	}, {
		"userid": "22231421",
		"userhead": "http://pic.qiushibaike.com/system/avtnew/2223/22231421/thumb/20141031073318.jpg",
		"username": "不会浪漫1978",
		"comment": "牛会踹的，明哥还活着吗？\u0001[发呆]",
		"sum": "30"
	}, {
		"userid": "31104875",
		"userhead": "http://pic.qiushibaike.com/system/avtnew/3110/31104875/thumb/20160203123124.jpg",
		"username": "渐渐的就不见了1",
		"comment": "不是屁股里？",
		"sum": "29"
	}, {
		"userid": "32776095",
		"userhead": "http://pic.qiushibaike.com/system/avtnew/3277/32776095/thumb/2016111620341752.JPEG",
		"username": "刘保强",
		"comment": "明哥biu的一声就钻进去了",
		"sum": "28"
	}, {
		"userid": "26509032",
		"userhead": "http://pic.qiushibaike.com/system/avtnew/2650/26509032/thumb/20150311230735.jpg",
		"username": "老衲爬墙头",
		"comment": "这么着急回家？",
		"sum": "27"
	}, {
		"userid": "31627118",
		"userhead": "http://pic.qiushibaike.com/system/avtnew/3162/31627118/thumb/2016120710043064.JPEG",
		"username": "amy9五个一",
		"comment": "一头攮进了NB里",
		"sum": "26"
	}, {
		"userid": "30840568",
		"userhead": "http://pic.qiushibaike.com/system/avtnew/3084/30840568/thumb/20151224181945.jpg",
		"username": "☆栋·邪★",
		"comment": "一个猛子扎牛逼，厉害了",
		"sum": "25"
	}, {
		"userid": "31780940",
		"userhead": "http://pic.qiushibaike.com/system/avtnew/3178/31780940/thumb/20160621001733.jpg",
		"username": "大海啊飘起来",
		"comment": "中国哪里还有清澈的河水",
		"sum": "24"
	}, {
		"userid": "27420908",
		"userhead": "http://pic.qiushibaike.com/system/avtnew/2742/27420908/thumb/20151117231723.jpg",
		"username": "小黑美眉的小白哥",
		"comment": "明哥何许淫也？虚哥吗？",
		"sum": "23"
	}, {
		"userid": "11578551",
		"userhead": "http://pic.qiushibaike.com/system/avtnew/1157/11578551/thumb/2016112807092128.JPEG",
		"username": "小肉卷",
		"comment": "我就想知道头插进去了没？",
		"sum": "22"
	}, {
		"userid": "24595605",
		"userhead": "http://pic.qiushibaike.com/system/avtnew/2459/24595605/thumb/20150108013827.jpg",
		"username": "月无情水无痕",
		"comment": "小明什么时候收小弟的",
		"sum": "21"
	}, {
		"userid": "20031151",
		"userhead": "http://pic.qiushibaike.com/system/avtnew/2003/20031151/thumb/nopic.jpg",
		"username": "你是2b1211",
		"comment": "我想知道回来怎么了",
		"sum": "20"
	}, {
		"userid": "32730143",
		"userhead": "http://pic.qiushibaike.com/system/avtnew/3273/32730143/thumb/2016100115570086.JPEG",
		"username": "九幽寒冰",
		"comment": "然后水牛向后就一蹄子，明哥去泰国谋生了！",
		"sum": "19"
	}, {
		"userid": "12651485",
		"userhead": "http://pic.qiushibaike.com/system/avtnew/1265/12651485/thumb/20140314002842.jpg",
		"username": "那个名字已注册",
		"comment": "回复 9楼：为什么要扎猛子呢？他们有仇吗",
		"sum": "18"
	}, {
		"userid": "12651485",
		"userhead": "http://pic.qiushibaike.com/system/avtnew/1265/12651485/thumb/20140314002842.jpg",
		"username": "那个名字已注册",
		"comment": "为什么要扎猛子呢？他们说",
		"sum": "17"
	}, {
		"userid": "21333057",
		"userhead": "http://pic.qiushibaike.com/system/avtnew/2133/21333057/thumb/201612020135167.JPEG",
		"username": "【蘑菇】大仙",
		"comment": "一头扎进去了，一群小伙伴拉着明哥两条腿，不对，三条腿，拼命往外拽，用力，用力……出来了，快出来了………用力啊！！！",
		"sum": "16"
	}, {
		"userid": "27054624",
		"userhead": "http://pic.qiushibaike.com/system/avtnew/2705/27054624/thumb/2016120620573930.JPEG",
		"username": "じ飘翎雁",
		"comment": "你们几个合力才把他拔出来的吧",
		"sum": "15"
	}, {
		"userid": "14790616",
		"userhead": "http://pic.qiushibaike.com/system/avtnew/1479/14790616/thumb/20140818114905.jpg",
		"username": "did大姐夫",
		"comment": "然后明哥起来搂着母牛吹牛逼了吧",
		"sum": "14"
	}, {
		"userid": "10606806",
		"userhead": "http://pic.qiushibaike.com/system/avtnew/1060/10606806/thumb/2016120219293146.JPEG",
		"username": "【星空】忧伤",
		"comment": "卧槽，真的有人能用头顶牛…还是顶的牛屁股",
		"sum": "13"
	}, {
		"userid": "28711746",
		"userhead": "http://pic.qiushibaike.com/system/avtnew/2871/28711746/thumb/201609210221000.JPEG",
		"username": "【星空】小静",
		"comment": "这么厉害",
		"sum": "12"
	}, {
		"userid": "30201529",
		"userhead": "http://pic.qiushibaike.com/system/avtnew/3020/30201529/thumb/2016092816272530.JPEG",
		"username": "【星空】堂主",
		"comment": "然后一头牛屎",
		"sum": "11"
	}, {
		"userid": "12992639",
		"userhead": "http://pic.qiushibaike.com/system/avtnew/1299/12992639/thumb/20160414185851.jpg",
		"username": "胖香",
		"comment": "卧槽！撒泼完毕，走人！",
		"sum": "10"
	}, {
		"userid": "12992639",
		"userhead": "http://pic.qiushibaike.com/system/avtnew/1299/12992639/thumb/20160414185851.jpg",
		"username": "胖香",
		"comment": "卧槽！抖哥有没有也这么做，去怼了牛屁股，，\u0001[幻想]",
		"sum": "9"
	}, {
		"userid": "12992639",
		"userhead": "http://pic.qiushibaike.com/system/avtnew/1299/12992639/thumb/20160414185851.jpg",
		"username": "胖香",
		"comment": "卧槽！那牛当时什么表情？",
		"sum": "8"
	}, {
		"userid": "12992639",
		"userhead": "http://pic.qiushibaike.com/system/avtnew/1299/12992639/thumb/20160414185851.jpg",
		"username": "胖香",
		"comment": "卧槽！太污了，重新评论，从那天起，那头牛就爱上了明哥，，",
		"sum": "7"
	}, {
		"userid": "12992639",
		"userhead": "http://pic.qiushibaike.com/system/avtnew/1299/12992639/thumb/20160414185851.jpg",
		"username": "胖香",
		"comment": "卧槽，头进去了没？",
		"sum": "6"
	}, {
		"userid": "30501602",
		"userhead": "http://pic.qiushibaike.com/system/avtnew/3050/30501602/thumb/2016112507515575.JPEG",
		"username": "巫女～<素素>",
		"comment": "扎猛子\u0001[大笑]\u0001[大笑]\u0001[大笑]",
		"sum": "5"
	}, {
		"userid": "29154820",
		"userhead": "http://pic.qiushibaike.com/system/avtnew/2915/29154820/thumb/2016120621455274.JPEG",
		"username": "岁月是把杀豬刀",
		"comment": "吹牛逼，吹牛逼，又见明哥吹牛逼。。。。",
		"sum": "4"
	}, {
		"userid": "32814675",
		"userhead": "http://pic.qiushibaike.com/system/avtnew/3281/32814675/thumb/2016112223402821.JPEG",
		"username": "鲨鱼姑娘",
		"comment": "牛逼大了\u0001[doge]\u0001[doge]",
		"sum": "3"
	}, {
		"userid": "28437800",
		"userhead": "http://pic.qiushibaike.com/system/avtnew/2843/28437800/thumb/2016112723370321.JPEG",
		"username": "【星空】白月光",
		"comment": "看热闹了看热闹了，明哥要倒霉了\u0001[笑哭]\u0001[笑哭]",
		"sum": "2"
	}, {
		"userid": "29248956",
		"userhead": "http://pic.qiushibaike.com/system/avtnew/2924/29248956/thumb/2016120115244373.JPEG",
		"username": "【星空】小燕飞",
		"comment": "这个撞的是母牛吧？我擦",
		"sum": "1"
	}]
}